Metadata-Version: 2.1
Name: yfapi
Version: 1.6.1
Summary: An unofficial library to capture data from Yahoo Finance API in an easier way. Having access to capture data from various stocks provided by the service.
Home-page: https://github.com/SrRenks/YahoofinanceAPI
Author: Ricardo Castro
Author-email: srrenks@gmail.com
License: MIT
Platform: UNKNOWN
License-File: LICENSE
